.gitignore
.readthedocs.yml
LICENSE.txt
MANIFEST.in
README.rst
setup.cfg
setup.py
.github/workflows/Build-and-Test.yml
NetworkSim/__init__.py
NetworkSim.egg-info/PKG-INFO
NetworkSim.egg-info/SOURCES.txt
NetworkSim.egg-info/dependency_links.txt
NetworkSim.egg-info/requires.txt
NetworkSim.egg-info/top_level.txt
NetworkSim/architecture/__init__.py
NetworkSim/architecture/base/__init__.py
NetworkSim/architecture/base/network.py
NetworkSim/architecture/base/node.py
NetworkSim/architecture/base/ring.py
NetworkSim/architecture/setup/__init__.py
NetworkSim/architecture/setup/model.py
NetworkSim/architecture/signal/__init__.py
NetworkSim/architecture/signal/control.py
NetworkSim/architecture/signal/data.py
NetworkSim/simulation/__init__.py
NetworkSim/simulation/process/__init__.py
NetworkSim/simulation/process/ram.py
NetworkSim/simulation/process/receiver/__init__.py
NetworkSim/simulation/process/receiver/base.py
NetworkSim/simulation/process/receiver/fixed.py
NetworkSim/simulation/process/receiver/fixed_downstream.py
NetworkSim/simulation/process/receiver/fixed_upstream.py
NetworkSim/simulation/process/receiver/tunable.py
NetworkSim/simulation/process/transmitter/__init__.py
NetworkSim/simulation/process/transmitter/base.py
NetworkSim/simulation/process/transmitter/fixed.py
NetworkSim/simulation/process/transmitter/tunable.py
NetworkSim/simulation/process/transmitter/tunable_downstream.py
NetworkSim/simulation/process/transmitter/tunable_upstream.py
NetworkSim/simulation/simulator/__init__.py
NetworkSim/simulation/simulator/base.py
NetworkSim/simulation/simulator/parallel.py
NetworkSim/simulation/tools/__init__.py
NetworkSim/simulation/tools/clock.py
NetworkSim/simulation/tools/distribution.py
NetworkSim/simulation/tools/info.py
NetworkSim/simulation/tools/load_save.py
NetworkSim/simulation/tools/performance_analysis.py
NetworkSim/simulation/tools/plot.py
NetworkSim/simulation/tools/presentation.py
NetworkSim/simulation/tools/publication.py
NetworkSim/simulation/tools/summary.py
NetworkSim/system_verilog/__init__.py
NetworkSim/system_verilog/receiver.py
NetworkSim/system_verilog/transmitter.py
NetworkSim/tests/__init__.py
