Metadata-Version: 2.1
Name: NetworkSim
Version: 0.2.2
Summary: A WDM ring datacentre network simulator
Home-page: https://github.com/HYang1996/NetworkSim
Maintainer: Hongyi Yang
Maintainer-email: zceehya@ucl.ac.uk
License: MIT
Download-URL: https://github.com/HYang1996/NetworkSim/archive/refs/tags/0.2.2.tar.gz
Platform: UNKNOWN
Classifier: Development Status :: 5 - Production/Stable
Classifier: Intended Audience :: Science/Research
Classifier: Intended Audience :: Developers
Classifier: Topic :: Software Development
Classifier: Topic :: Scientific/Engineering
Classifier: License :: OSI Approved :: MIT License
Classifier: Programming Language :: Python :: 3.6
Classifier: Programming Language :: Python :: 3.7
Classifier: Programming Language :: Python :: 3.8
